[
  {
    "id": "cosecha-maiz",
    "titulo": "Temporada de Cosecha de Maíz",
    "categoria": "agricultura",
    "resumen": "Nuestros campos se tiñen de dorado con la producción de maíz de la mejor calidad.",
    "contenido": "Gracias al clima privilegiado de nuestra región, el maíz de Alfonso Ugarte es reconocido por su tamaño y sabor. Los agricultores locales mantienen técnicas ancestrales de riego...",
    "imagen": "assets/images/agricultura/maizal.jpg",
    "fecha": "2026-04-12"
  },
  {
    "id": "produccion-papa",
    "titulo": "Variedades de Papa Nativa",
    "categoria": "agricultura",
    "resumen": "Conoce las diversas clases de papas que se cultivan en las tierras altas de nuestro distrito.",
    "contenido": "Desde la papa amarilla hasta las variedades nativas menos conocidas, nuestro suelo ofrece una riqueza nutricional incomparable. Promovemos la agricultura orgánica y sostenible...",
    "imagen": "assets/images/agricultura/papas.jpg",
    "fecha": "2026-06-01"
  }
]